UniformSumDistribution/UniformSumDistribution.py
UniformSumDistribution/__init__.py
UniformSumDistribution-1.0.3.dist-info/LICENSE
UniformSumDistribution-1.0.3.dist-info/METADATA
UniformSumDistribution-1.0.3.dist-info/WHEEL
UniformSumDistribution-1.0.3.dist-info/top_level.txt
UniformSumDistribution-1.0.3.dist-info/RECORD
