Metadata-Version: 2.1
Name: UniformSumDistribution
Version: 1.0.3
Summary: Implementation of the Irwin-Hall (the uniform sum) distribution
Home-page: https://github.com/artyom-zolotarevskiy/UniformSumDistribution
Author: Artyom Zolotarevskiy
Author-email: artyom@zolotarevskiy.com
License: MIT
Project-URL: Bug Tracker, https://github.com/artyom-zolotarevskiy/UniformSumDistribution/issues
Platform: UNKNOWN
Classifier: Programming Language :: Python :: 3
Classifier: License :: OSI Approved :: MIT License
Classifier: Operating System :: OS Independent
License-File: LICENSE
Requires-Dist: numpy
Requires-Dist: scipy
